ws_wi_sync/__init__.py
ws_wi_sync/_version.py
ws_wi_sync/config.py
ws_wi_sync/core.py
ws_wi_sync/ws_wi_integration.py
ws_wi_integration-0.0.1.dist-info/LICENSE
ws_wi_integration-0.0.1.dist-info/METADATA
ws_wi_integration-0.0.1.dist-info/WHEEL
ws_wi_integration-0.0.1.dist-info/entry_points.txt
ws_wi_integration-0.0.1.dist-info/top_level.txt
ws_wi_integration-0.0.1.dist-info/RECORD
