Metadata-Version: 2.1
Name: ws-wi-integration
Version: 0.0.1
Summary: WI Integration
Home-page: UNKNOWN
Author: WhiteSource Professional Services
Author-email: ps@whitesourcesoftware.com
License: LICENSE.txt
Platform: UNKNOWN
Classifier: Programming Language :: Python :: 3.8
Classifier: Programming Language :: Python :: 3.9
Classifier: Programming Language :: Python :: 3.10
Classifier: License :: OSI Approved :: Apache Software License
Classifier: Operating System :: OS Independent
Requires-Python: >=3.8
Requires-Dist: DateTime (==4.4)
Requires-Dist: certifi (==2022.5.18.1)
Requires-Dist: charset-normalizer (==2.0.12)
Requires-Dist: idna (==3.3)
Requires-Dist: isodate (==0.6.1)
Requires-Dist: msrest (==0.6.21)
Requires-Dist: oauthlib (==3.2.0)
Requires-Dist: pytz (==2022.1)
Requires-Dist: requests-oauthlib (==1.3.1)
Requires-Dist: requests (==2.27.1)
Requires-Dist: six (==1.16.0)
Requires-Dist: sqlparse (==0.4.2)
Requires-Dist: tzdata (==2022.1)
Requires-Dist: urllib3 (==1.26.9)
Requires-Dist: vsts (==0.1.25)
Requires-Dist: wheel
Requires-Dist: ws-sdk (==0.9.3)
Requires-Dist: zope.interface (==5.4.0)
